tests/__init__.py
tests/unit/__init__.py
tests/unit/constants.py
tests/unit/test__chatmemberupdated.py
tests/unit/test_base.py
tests/unit/test_bot.py
tests/unit/test_bot_command.py
tests/unit/test_callback_query.py
tests/unit/test_chat.py
tests/unit/test_chatinvitelink.py
tests/unit/test_chatlocation.py
tests/unit/test_chatmember.py
tests/unit/test_chatpermissions.py
tests/unit/test_constants.py
tests/unit/test_errors.py
tests/unit/test_file.py
tests/unit/test_loginurl.py
tests/unit/test_messageentity.py
tests/unit/test_messageid.py
tests/unit/test_parsemode.py
tests/unit/test_proximityalerttriggered.py
tests/unit/test_update.py
tests/unit/test_userprofilephotos.py
tests/unit/test_webhookinfo.py
tests/unit/test_files/__init__.py
tests/unit/test_files/test_animation.py
tests/unit/test_files/test_audio.py
tests/unit/test_files/test_chatphoto.py
tests/unit/test_files/test_contact.py
tests/unit/test_files/test_document.py
tests/unit/test_files/test_location.py
tests/unit/test_files/test_photosize.py
tests/unit/test_files/test_sticker.py
tests/unit/test_files/test_venue.py
tests/unit/test_files/test_video.py
tests/unit/test_files/test_video_note.py
tests/unit/test_files/test_voice.py
tests/unit/test_keyboard/__init__.py
tests/unit/test_keyboard/test_inline_keyboard.py
tests/unit/test_keyboard/test_inline_keyboard_button.py
tests/unit/test_keyboard/test_reply_keyboard_remove.py
tests/unit/test_keyboard/test_reply_markup.py
tests/unit/test_media/__init__.py
tests/unit/test_media/test__inputmediaanimation.py
tests/unit/test_media/test__inputmediaaudio.py
tests/unit/test_media/test__inputmediadocument.py
tests/unit/test_media/test__inputmediaphoto.py
tests/unit/test_media/test__inputmediavideo.py
tests/unit/test_passport/__init__.py
tests/unit/test_passport/test_encryptedcredentials.py
tests/unit/test_passport/test_encryptedpassportelement.py
tests/unit/test_passport/test_passportdata.py
tests/unit/test_passport/test_passportfile.py
tests/unit/test_payments/__init__.py
tgsdk-1.3.0.dist-info/LICENSE
tgsdk-1.3.0.dist-info/METADATA
tgsdk-1.3.0.dist-info/WHEEL
tgsdk-1.3.0.dist-info/top_level.txt
tgsdk-1.3.0.dist-info/RECORD
